mycalc/calculator.py
gyulim2024-0.0.1.dist-info/LICENSE
gyulim2024-0.0.1.dist-info/METADATA
gyulim2024-0.0.1.dist-info/WHEEL
gyulim2024-0.0.1.dist-info/top_level.txt
gyulim2024-0.0.1.dist-info/RECORD
