Metadata-Version: 2.1
Name: gyulim2024
Version: 0.0.1
Summary: nice calculator
Home-page: https://github.com/kuelim/calc0001
Author: gyulim
Classifier: Programming Language :: Python :: 3
License-File: LICENSE
